dblist/__init__.py
dblist/api.py
dblist/base.py
dblist/init_db.py
dblist/models.py
dblist-0.1.0.dist-info/METADATA
dblist-0.1.0.dist-info/WHEEL
dblist-0.1.0.dist-info/top_level.txt
dblist-0.1.0.dist-info/RECORD
