Metadata-Version: 2.1
Name: dblist
Version: 0.1.0
Summary: Storage of lists and Numpy arrays within relational databases, using SQLAlchemy.
Home-page: UNKNOWN
Author: Adam J. Plowman
Author-email: UNKNOWN
License: UNKNOWN
Platform: UNKNOWN
Classifier: Development Status :: 3 - Alpha
Requires-Dist: sqlalchemy
Requires-Dist: numpy
